<?xml version="1.0" encoding="UTF-8"?>
<ItemCollection>
  <Items>
<Item name = "jet_0">
<title>PF jet</title>
<pt>95.5896</pt>
<eta>0.900418</eta>
<phi>2.6923</phi>
</Item>
<Item name = "jet_1">
<title>PF jet</title>
<pt>48.8528</pt>
<eta>0.68329</eta>
<phi>0.650001</phi>
</Item>
<Item name = "jet_2">
<title>PF jet</title>
<pt>44.8501</pt>
<eta>2.21161</eta>
<phi>-0.994216</phi>
</Item>
<Item name = "electron_0">
<title>Electron</title>
<pt>24.1542</pt>
<eta>0.595832</eta>
<phi>-2.99584</phi>
<charge>1</charge>
</Item>
<Item name = "MET">
<title>PF MET</title>
<pt>78.1951</pt>
<phi>-0.432391</phi>
</Item>
  </Items>
</ItemCollection>
